dateHandler/__init__.py
dateHandler/dateController.py
dateHandler-0.0.2.dist-info/METADATA
dateHandler-0.0.2.dist-info/WHEEL
dateHandler-0.0.2.dist-info/top_level.txt
dateHandler-0.0.2.dist-info/RECORD
