Metadata-Version: 2.1
Name: dateHandler
Version: 0.0.2
Summary: Dates Handler - simple method for date manipulation
Home-page: UNKNOWN
Author: Alexandre Suire
Author-email: UNKNOWN
License: UNKNOWN
Keywords: python,dates
Platform: UNKNOWN
Classifier: Development Status :: 3 - Alpha
Classifier: Intended Audience :: Developers
Classifier: Programming Language :: Python :: 3
Classifier: Operating System :: MacOS :: MacOS X
Classifier: Operating System :: Microsoft :: Windows
Requires-Dist: arrow
